psann/__init__.py
psann/_aliases.py
psann/activations.py
psann/attention.py
psann/conv.py
psann/embeddings.py
psann/episodes.py
psann/hisso.py
psann/initializers.py
psann/lsm.py
psann/metrics.py
psann/nn.py
psann/nn_geo_sparse.py
psann/params.py
psann/preproc.py
psann/rewards.py
psann/sklearn.py
psann/state.py
psann/tokenizer.py
psann/training.py
psann/types.py
psann/estimators/_fit_utils.py
psann/layers/__init__.py
psann/layers/film.py
psann/layers/geo_sparse.py
psann/layers/sine_residual.py
psann/layers/spectral.py
psann/lm/__init__.py
psann/models/__init__.py
psann/models/wave_encoder.py
psann/models/wave_resnet.py
psann/models/wave_rnn.py
psann/utils/__init__.py
psann/utils/diagnostics.py
psann/utils/hf_cache.py
psann/utils/linear_probe.py
psann/utils/synthetic.py
psann-0.12.2.dist-info/METADATA
psann-0.12.2.dist-info/WHEEL
psann-0.12.2.dist-info/licenses/LICENSE
psann-0.12.2.dist-info/RECORD
