Metadata-Version: 2.4
Name: psann
Version: 0.12.2
Summary: PSANN: Parameterized Sine-Activated Neural Networks (primary-output, sklearn-style, PyTorch backend)
Project-URL: Homepage, https://github.com/psann-project/psann
Project-URL: Repository, https://github.com/psann-project/psann
Project-URL: Issues, https://github.com/psann-project/psann/issues
Project-URL: Documentation, https://github.com/psann-project/psann/tree/main/docs
Project-URL: Changelog, https://github.com/psann-project/psann/blob/main/docs/migration.md
Project-URL: Contributing, https://github.com/psann-project/psann/blob/main/docs/CONTRIBUTING.md
Author: Nicholas Milinkovich
License: MIT License
License-File: LICENSE
Keywords: classification,neural-networks,pytorch,regression,sine,siren,sklearn,time-series
Classifier: Development Status :: 3 - Alpha
Classifier: Intended Audience :: Developers
Classifier: Intended Audience :: Science/Research
Classifier: License :: OSI Approved :: MIT License
Classifier: Operating System :: OS Independent
Classifier: Programming Language :: Python :: 3
Classifier: Programming Language :: Python :: 3 :: Only
Classifier: Topic :: Scientific/Engineering :: Artificial Intelligence
Requires-Python: >=3.9
Requires-Dist: numpy>=1.23
Requires-Dist: torch>=2.1
Provides-Extra: compat
Requires-Dist: numpy==1.26.4; extra == 'compat'
Requires-Dist: scikit-learn==1.4.2; extra == 'compat'
Requires-Dist: scipy==1.11.4; extra == 'compat'
Requires-Dist: torch==2.1.2; extra == 'compat'
Provides-Extra: dev
Requires-Dist: black>=24.0; extra == 'dev'
Requires-Dist: build>=1.2; extra == 'dev'
Requires-Dist: coverage[toml]>=7.5; extra == 'dev'
Requires-Dist: mypy>=1.10; extra == 'dev'
Requires-Dist: pre-commit>=3.6; extra == 'dev'
Requires-Dist: pytest-json-report>=1.5; extra == 'dev'
Requires-Dist: pytest>=7.0; extra == 'dev'
Requires-Dist: ruff>=0.5.0; extra == 'dev'
Provides-Extra: sklearn
Requires-Dist: scikit-learn<1.5,>=1.2; extra == 'sklearn'
Provides-Extra: viz
Requires-Dist: matplotlib>=3.7; extra == 'viz'
